examon_repo_1/__init__.py
examon_repo_1/abc.py
examon_repo_1/assignment.py
examon_repo_1/basic.py
examon_repo_1/built_in1.py
examon_repo_1/bytes.py
examon_repo_1/classes.py
examon_repo_1/collections_1.py
examon_repo_1/dataclasses.py
examon_repo_1/decorators_1.py
examon_repo_1/dict_1.py
examon_repo_1/dunder_1.py
examon_repo_1/exceptions.py
examon_repo_1/fa.py
examon_repo_1/first_class_functions.py
examon_repo_1/functools.py
examon_repo_1/generators.py
examon_repo_1/hashing.py
examon_repo_1/inheritance.py
examon_repo_1/itertools.py
examon_repo_1/list_1.py
examon_repo_1/list_comps_1.py
examon_repo_1/math1.py
examon_repo_1/operator_overloading.py
examon_repo_1/protocols.py
examon_repo_1/references.py
examon_repo_1/set_1.py
examon_repo_1/slicing_1.py
examon_repo_1/string.py
examon_repo_1/unpacking_1.py
examon_repo_1/with1.py
examon_repo_1-1.0.2.dist-info/METADATA
examon_repo_1-1.0.2.dist-info/WHEEL
examon_repo_1-1.0.2.dist-info/RECORD
